pgdumplib/__init__.py
pgdumplib/constants.py
pgdumplib/converters.py
pgdumplib/dump.py
pgdumplib/exceptions.py
pgdumplib-1.0.1.dist-info/LICENSE
pgdumplib-1.0.1.dist-info/METADATA
pgdumplib-1.0.1.dist-info/WHEEL
pgdumplib-1.0.1.dist-info/top_level.txt
pgdumplib-1.0.1.dist-info/zip-safe
pgdumplib-1.0.1.dist-info/RECORD
