Metadata-Version: 2.1
Name: pgdumplib
Version: 1.0.1
Summary: Python3 library for working with pg_dump files
Home-page: https://github.com/gmr/pgdumplib
Author: Gavin M. Roy
Author-email: gavinmroy@gmail.com
License: BSD 3-Clause License
Platform: UNKNOWN
Classifier: Development Status :: 4 - Beta
Classifier: Intended Audience :: Developers
Classifier: License :: OSI Approved :: BSD License
Classifier: Natural Language :: English
Classifier: Operating System :: OS Independent
Classifier: Programming Language :: Python :: 3
Classifier: Programming Language :: Python :: 3.7
Classifier: Programming Language :: Python :: Implementation :: CPython
Classifier: Topic :: Database
Classifier: Topic :: Software Development :: Libraries
Classifier: Topic :: Software Development :: Libraries :: Python Modules
Requires-Dist: arrow
